{
  "AGEAC": {
    "eixos": {
      "Eixo II – Mitigação das Mudanças Climáticas": 1000.0
    },
    "total": 1000.0
  },
  "AGEAC (SEOP)": {
    "eixos": {
      "Eixo II – Mitigação das Mudanças Climáticas": 550000.0
    },
    "total": 550000.0
  },
  "ANAC": {
    "eixos": {
      "Eixo I – Desenvolvimento Sustentável e Bioeconomia": 1385928.7
    },
    "total": 1385928.7
  },
  "CAGEACRE": {
    "eixos": {
      "Eixo I – Desenvolvimento Sustentável e Bioeconomia": 1220809.49
    },
    "total": 1220809.49
  },
  "CBMAC": {
    "eixos": {
      "Eixo VII – Resposta Climática Emergencial e Proteção Civil": 593667.0
    },
    "total": 593667.0
  },
  "CDSA": {
    "eixos": {
      "Eixo I – Desenvolvimento Sustentável e Bioeconomia": 804910.8
    },
    "total": 804910.8
  },
  "CGE": {
    "eixos": {
      "Eixo V – Governança Ambiental e Transparência": 660000.0
    },
    "total": 660000.0
  },
  "COORD. EST. PROTEÇÃO E DEFESA CIVIL": {
    "eixos": {
      "Eixo VII – Resposta Climática Emergencial e Proteção Civil": 17753000.0
    },
    "total": 17753000.0
  },
  "DERACRE (SEHURB)": {
    "eixos": {
      "Eixo II – Mitigação das Mudanças Climáticas": 102023031.49000001
    },
    "total": 102023031.49000001
  },
  "EMATER": {
    "eixos": {
      "Eixo I – Desenvolvimento Sustentável e Bioeconomia": 2442771.45
    },
    "total": 2442771.45
  },
  "FAPAC": {
    "eixos": {
      "Eixo VI – Educação Ambiental e Inovação Climática": 1156490.0
    },
    "total": 1156490.0
  },
  "FUNTAC": {
    "eixos": {
      "Eixo VI – Educação Ambiental e Inovação Climática": 700110.0
    },
    "total": 700110.0
  },
  "IMAC": {
    "eixos": {
      "Eixo II – Mitigação das Mudanças Climáticas": 6653714.85,
      "Eixo VI – Educação Ambiental e Inovação Climática": 1000.0
    },
    "total": 6654714.85
  },
  "IMC": {
    "eixos": {
      "Eixo II – Mitigação das Mudanças Climáticas": 271000.0,
      "Eixo V – Governança Ambiental e Transparência": 3000.0
    },
    "total": 274000.0
  },
  "ITERACRE (SEHURB)": {
    "eixos": {
      "Eixo IV – Justiça Climática e Inclusão Social": 12187135.52
    },
    "total": 12187135.52
  },
  "JUCEAC (SEFAZ)": {
    "eixos": {
      "Eixo I – Desenvolvimento Sustentável e Bioeconomia": 1361000.0
    },
    "total": 1361000.0
  },
  "PROCON (SEASDH)": {
    "eixos": {
      "Eixo IV – Justiça Climática e Inclusão Social": 4839000.0
    },
    "total": 4839000.0
  },
  "SANEACRE": {
    "eixos": {
      "Eixo II – Mitigação das Mudanças Climáticas": 31000.0
    },
    "total": 31000.0
  },
  "SEAD": {
    "eixos": {
      "Eixo II – Mitigação das Mudanças Climáticas": 1000.0
    },
    "total": 1000.0
  },
  "SEADH (Fundo Estadual de Defesa do Consumidor (FEDC))": {
    "eixos": {
      "Eixo IV – Justiça Climática e Inclusão Social": 1030000.0
    },
    "total": 1030000.0
  },
  "SEAGRI": {
    "eixos": {
      "Eixo I – Desenvolvimento Sustentável e Bioeconomia": 102195200.0
    },
    "total": 102195200.0
  },
  "SEAGRI (Fundo Agropecuário (FUNAGRO))": {
    "eixos": {
      "Eixo I – Desenvolvimento Sustentável e Bioeconomia": 2000000.0
    },
    "total": 2000000.0
  },
  "SEASDH": {
    "eixos": {
      "Eixo IV – Justiça Climática e Inclusão Social": 7528000.0
    },
    "total": 7528000.0
  },
  "SEASDH (Fundo de Assistência Social (FEAS))": {
    "eixos": {
      "Eixo IV – Justiça Climática e Inclusão Social": 829000.0
    },
    "total": 829000.0
  },
  "SEE": {
    "eixos": {
      "Eixo IV – Justiça Climática e Inclusão Social": 65200.0
    },
    "total": 65200.0
  },
  "SEFAZ": {
    "eixos": {
      "Eixo I – Desenvolvimento Sustentável e Bioeconomia": 5000000.0,
      "Eixo II – Mitigação das Mudanças Climáticas": 1000.0
    },
    "total": 5001000.0
  },
  "SEHURB": {
    "eixos": {
      "Eixo IV – Justiça Climática e Inclusão Social": 1151000.0
    },
    "total": 1151000.0
  },
  "SEICT": {
    "eixos": {
      "Eixo I – Desenvolvimento Sustentável e Bioeconomia": 1315393.95
    },
    "total": 1315393.95
  },
  "SEICT (Fundo de Des. Sustentável (FDS))": {
    "eixos": {
      "Eixo VI – Educação Ambiental e Inovação Climática": 1020000.0
    },
    "total": 1020000.0
  },
  "SEICT (Fundo de Desenv. Sustentável (FDS))": {
    "eixos": {
      "Eixo I – Desenvolvimento Sustentável e Bioeconomia": 1090000.0
    },
    "total": 1090000.0
  },
  "SEICT (Fundo de Desenvolvimento Sustentável (FDS))": {
    "eixos": {
      "Eixo I – Desenvolvimento Sustentável e Bioeconomia": 3890000.0
    },
    "total": 3890000.0
  },
  "SEJUSP": {
    "eixos": {
      "Eixo II – Mitigação das Mudanças Climáticas": 1198684.01
    },
    "total": 1198684.01
  },
  "SEJUSP (Fundo Est. de Segurança (FUNDESEG))": {
    "eixos": {
      "Eixo II – Mitigação das Mudanças Climáticas": 1000.0
    },
    "total": 1000.0
  },
  "SEMA": {
    "eixos": {
      "Eixo I – Desenvolvimento Sustentável e Bioeconomia": 4023000.0,
      "Eixo II – Mitigação das Mudanças Climáticas": 12633154.370000001,
      "Eixo V – Governança Ambiental e Transparência": 11000.0
    },
    "total": 16667154.370000001
  },
  "SEMA (Fundo Est. de Comando e Controle Ambiental)": {
    "eixos": {
      "Eixo II – Mitigação das Mudanças Climáticas": 5004200.0
    },
    "total": 5004200.0
  },
  "SEMA (Fundo Est. de Meio Ambiente e Florestas)": {
    "eixos": {
      "Eixo I – Desenvolvimento Sustentável e Bioeconomia": 1000.0,
      "Eixo II – Mitigação das Mudanças Climáticas": 2000.0
    },
    "total": 3000.0
  },
  "SEMA (Fundo Estadual de Comando e Cont. Ambiental)": {
    "eixos": {
      "Eixo VI – Educação Ambiental e Inovação Climática": 1000.0
    },
    "total": 1000.0
  },
  "SEMULHER": {
    "eixos": {
      "Eixo IV – Justiça Climática e Inclusão Social": 478000.0
    },
    "total": 478000.0
  },
  "SEPI": {
    "eixos": {
      "Eixo IV – Justiça Climática e Inclusão Social": 4000.0
    },
    "total": 4000.0
  },
  "SEPLAN": {
    "eixos": {
      "Eixo II – Mitigação das Mudanças Climáticas": 244802888.98
    },
    "total": 244802888.98
  }
}